nonebot_plugin_remake/__init__.py
nonebot_plugin_remake/age.py
nonebot_plugin_remake/drawer.py
nonebot_plugin_remake/event.py
nonebot_plugin_remake/life.py
nonebot_plugin_remake/property.py
nonebot_plugin_remake/resources/data/age.json
nonebot_plugin_remake/resources/data/events.json
nonebot_plugin_remake/resources/data/talents.json
nonebot_plugin_remake/resources/fonts/方正像素12.ttf
nonebot_plugin_remake/resources/images/bg_summary.png
nonebot_plugin_remake/resources/images/bg_talent.png
nonebot_plugin_remake/resources/images/icon_chr.png
nonebot_plugin_remake/resources/images/icon_int.png
nonebot_plugin_remake/resources/images/icon_mny.png
nonebot_plugin_remake/resources/images/icon_spr.png
nonebot_plugin_remake/resources/images/icon_str.png
nonebot_plugin_remake/resources/images/title_left.png
nonebot_plugin_remake/resources/images/title_right.png
nonebot_plugin_remake/resources/images/titlebar.png
nonebot_plugin_remake/talent.py
nonebot_plugin_remake/utils.py
nonebot_plugin_remake-0.4.4.dist-info/LICENSE
nonebot_plugin_remake-0.4.4.dist-info/METADATA
nonebot_plugin_remake-0.4.4.dist-info/WHEEL
nonebot_plugin_remake-0.4.4.dist-info/RECORD
