Metadata-Version: 2.1
Name: nonebot_plugin_remake
Version: 0.4.4
Summary: 适用于 Nonebot2 的人生重开模拟器插件
Home-page: https://github.com/noneplugin/nonebot-plugin-remake
License: MIT
Author: meetwq
Author-email: meetwq@gmail.com
Requires-Python: >=3.9,<4.0
Classifier: License :: OSI Approved :: MIT License
Classifier: Programming Language :: Python :: 3
Classifier: Programming Language :: Python :: 3.9
Classifier: Programming Language :: Python :: 3.10
Classifier: Programming Language :: Python :: 3.11
Classifier: Programming Language :: Python :: 3.12
Classifier: Programming Language :: Python :: 3.13
Requires-Dist: Pillow (>=10.0.0,<12.0.0)
Requires-Dist: nonebot-plugin-alconna (>=0.46.3,<1.0.0)
Requires-Dist: nonebot2 (>=2.3.0,<3.0.0)
Project-URL: Repository, https://github.com/noneplugin/nonebot-plugin-remake
